magicbook/__init__.py
magicbook/__main__.py
magicbook/book_tools.py
magicbook/constants.py
magicbook/imposition_tools.py
magicbook/library_tools.py
magicbook/setup_tools.py
magicbook/simple_io_tools.py
magicbook/toc_tools.py
magicbook-0.0.3.dist-info/LICENSE.md
magicbook-0.0.3.dist-info/METADATA
magicbook-0.0.3.dist-info/WHEEL
magicbook-0.0.3.dist-info/entry_points.txt
magicbook-0.0.3.dist-info/RECORD
