Metadata-Version: 2.1
Name: magicbook
Version: 0.0.3
Summary: Sheet music management for large ensembles
License: AGPL-3.0
Keywords: sheet music
Author: Max
Requires-Python: >=3.12,<4.0
Classifier: Development Status :: 2 - Pre-Alpha
Classifier: Environment :: Console
Classifier: Intended Audience :: Education
Classifier: License :: OSI Approved :: GNU Affero General Public License v3
Classifier: Natural Language :: English
Classifier: Programming Language :: Python
Classifier: Programming Language :: Python :: 3
Classifier: Programming Language :: Python :: 3.12
Classifier: Topic :: Artistic Software
Classifier: Topic :: Printing
Requires-Dist: jsonschema (>=4.23.0,<5.0.0)
Requires-Dist: pip-licenses (>=5.0.0,<6.0.0)
Requires-Dist: pypdf (>=4.3.1,<5.0.0)
Requires-Dist: pyyaml (>=6.0.1,<7.0.0)
Requires-Dist: regex (>=2024.7.24,<2025.0.0)
Requires-Dist: reportlab (>=4.2.2,<5.0.0)
Requires-Dist: rich (>=13.7.1,<14.0.0)
Requires-Dist: rich-argparse (>=1.5.2,<2.0.0)
Requires-Dist: simple-term-menu (>=1.6.4,<2.0.0)
